[
    {
        "type": "message",
        "text": "Circle still sittin at 7",
        "user": "U15HSHSS2",
        "ts": "1522765939.000070"
    },
    {
        "client_msg_id": "5E30489F-6A7F-4A67-8CC0-43C01318968D",
        "type": "message",
        "text": "I saw one that got up in the 90s",
        "user": "U15J5H60P",
        "ts": "1522765976.000180"
    },
    {
        "type": "message",
        "text": "Yeah, I see one that got to 106",
        "user": "U15HSHSS2",
        "ts": "1522765999.000860"
    },
    {
        "client_msg_id": "9C0B6BA4-3AFE-4E02-964B-60840A90DEE0",
        "type": "message",
        "text": "Dang",
        "user": "U15J5H60P",
        "ts": "1522766008.000154"
    },
    {
        "client_msg_id": "090A9746-D6A2-448E-A451-15CAA03A7728",
        "type": "message",
        "text": "Lol",
        "user": "U15HY5TG8",
        "ts": "1522766022.000332"
    },
    {
        "client_msg_id": "C986A6AF-A3B3-4534-90DD-651F1BF79252",
        "type": "message",
        "text": "I dont get the betray thing",
        "user": "U15HY5TG8",
        "ts": "1522766029.000484"
    },
    {
        "type": "message",
        "text": "When you give someone the key to join your circle, they can choose to betray it if they want. Which \"deactivates\" it so no one else can join",
        "user": "U15HSHSS2",
        "ts": "1522766091.000115"
    },
    {
        "type": "message",
        "text": "the goal is to have the largest active circle",
        "user": "U15HSHSS2",
        "ts": "1522766112.000886"
    },
    {
        "client_msg_id": "FCA7F25E-9B00-41A3-9B7B-8EA39B1E8BB4",
        "type": "message",
        "text": "Interesting concept lol",
        "user": "U15HY5TG8",
        "ts": "1522766127.000865"
    },
    {
        "type": "message",
        "text": "did you join Andrews?",
        "user": "U15HSHSS2",
        "ts": "1522766143.000421"
    },
    {
        "client_msg_id": "915F0C2E-9475-43A0-9FE0-1EB8177EC8A8",
        "type": "message",
        "text": "I have not. I also just havent been on reddit in a long time",
        "user": "U15HY5TG8",
        "ts": "1522766179.000100"
    },
    {
        "type": "message",
        "text": "wtf do you do at work?",
        "user": "U15HSHSS2",
        "ts": "1522766192.000145"
    },
    {
        "client_msg_id": "0EC6EBD7-E68D-4598-9386-DA16A4314B8C",
        "type": "message",
        "text": "Work lol",
        "user": "U15HY5TG8",
        "ts": "1522766205.000324"
    },
    {
        "type": "message",
        "text": "Damn, that's crazy.",
        "user": "U15HSHSS2",
        "ts": "1522766218.000677"
    },
    {
        "type": "message",
        "text": "lol reddit is 60% of my day",
        "user": "U15HSHSS2",
        "ts": "1522766226.000715"
    },
    {
        "client_msg_id": "FFB5FF72-236C-4926-8E5F-A40386339ED3",
        "type": "message",
        "text": "I sit in a main area, so I cant just be pulling up fun sites willy nilly",
        "user": "U15HY5TG8",
        "ts": "1522766232.000084"
    },
    {
        "type": "message",
        "text": "booo",
        "user": "U15HSHSS2",
        "ts": "1522766238.000246"
    },
    {
        "client_msg_id": "F986C046-89DB-4BD8-81E5-40D8CD9D34C9",
        "type": "message",
        "text": "60% of your day lol",
        "user": "U15HY5TG8",
        "ts": "1522766253.000589"
    },
    {
        "bot_id": "B696MB84Q",
        "type": "message",
        "text": "",
        "user": "U15HRTAHL",
        "ts": "1522766256.000552",
        "attachments": [
            {
                "fallback": "giphy: https:\/\/giphy.com\/gifs\/everyone-trump-comprehensive-SvgmMm20VGHzq",
                "image_url": "https:\/\/media1.giphy.com\/media\/SvgmMm20VGHzq\/giphy-downsized.gif",
                "image_width": 320,
                "image_height": 174,
                "image_bytes": 1691046,
                "is_animated": true,
                "title": "trump sad",
                "footer": "Posted using \/giphy",
                "id": 1,
                "title_link": "https:\/\/giphy.com\/gifs\/everyone-trump-comprehensive-SvgmMm20VGHzq"
            }
        ]
    },
    {
        "type": "message",
        "text": "<https:\/\/www.reddit.com\/r\/CircleofTrust\/comments\/8931eb\/freeuwmke\/>",
        "user": "U15HSHSS2",
        "ts": "1522766259.000057",
        "attachments": [
            {
                "service_name": "reddit",
                "title": "FreeUWMKE • r\/CircleofTrust",
                "title_link": "https:\/\/www.reddit.com\/r\/CircleofTrust\/comments\/8931eb\/freeuwmke\/",
                "text": "1 points and 2 comments so far on reddit",
                "fallback": "reddit: FreeUWMKE • r\/CircleofTrust",
                "thumb_url": "https:\/\/www.redditstatic.com\/icon.png",
                "from_url": "https:\/\/www.reddit.com\/r\/CircleofTrust\/comments\/8931eb\/freeuwmke\/",
                "thumb_width": 256,
                "thumb_height": 256,
                "service_icon": "http:\/\/www.redditstatic.com\/desktop2x\/img\/favicon\/apple-icon-57x57.png",
                "id": 1
            }
        ]
    },
    {
        "type": "message",
        "text": "key = SeaMobileBlack",
        "user": "U15HSHSS2",
        "ts": "1522766271.000633"
    },
    {
        "client_msg_id": "E616476F-15C1-4D78-A6CB-4184176B520C",
        "type": "message",
        "text": "How do i enter it?",
        "user": "U15HY5TG8",
        "ts": "1522766329.000310"
    },
    {
        "type": "message",
        "text": "it should say \"unlock\" with a text box next to it",
        "user": "U15HSHSS2",
        "ts": "1522766356.000715"
    },
    {
        "type": "message",
        "text": "are you on mobile?",
        "user": "U15HSHSS2",
        "ts": "1522766376.000607"
    },
    {
        "client_msg_id": "58B2F5D4-32F1-4CC5-BF9C-C2BE66EDF833",
        "type": "message",
        "text": "Yea i was",
        "user": "U15HY5TG8",
        "ts": "1522766400.000645"
    },
    {
        "client_msg_id": "68264395-95FD-47FD-A814-F0DD1C6CAEFD",
        "type": "message",
        "text": "How do i betray?",
        "user": "U15HY5TG8",
        "ts": "1522766406.000136"
    },
    {
        "type": "message",
        "text": "lol",
        "user": "U15HSHSS2",
        "ts": "1522766410.000504"
    },
    {
        "type": "message",
        "text": "click \"betray\"",
        "user": "U15HSHSS2",
        "ts": "1522766419.000073"
    },
    {
        "type": "message",
        "text": "it has issues on mobile",
        "user": "U15HSHSS2",
        "ts": "1522766427.000830"
    },
    {
        "type": "message",
        "text": "I think it works if you load into desktop mode",
        "user": "U15HSHSS2",
        "ts": "1522766443.000662"
    },
    {
        "type": "message",
        "text": "I'm gonna betray",
        "user": "U15HY5TG8",
        "ts": "1522766445.000444"
    },
    {
        "type": "message",
        "text": "I just loaded it on my desktop",
        "user": "U15HY5TG8",
        "ts": "1522766453.000585"
    },
    {
        "type": "message",
        "text": "stupid phones",
        "user": "U15HY5TG8",
        "ts": "1522766457.000695"
    },
    {
        "type": "message",
        "text": "What does this do exactly?",
        "user": "U15HY5TG8",
        "ts": "1522766490.000838"
    },
    {
        "type": "message",
        "text": "ahyy",
        "user": "U15HSHSS2",
        "ts": "1522766494.000168"
    },
    {
        "type": "message",
        "text": "8 people !",
        "user": "U15HSHSS2",
        "ts": "1522766497.000680"
    },
    {
        "type": "message",
        "text": "lol",
        "user": "U15HY5TG8",
        "ts": "1522766503.000349"
    },
    {
        "type": "message",
        "text": "nothing really just a little social experiment\/compitition like they do every april fools",
        "user": "U15HSHSS2",
        "ts": "1522766524.000015"
    },
    {
        "type": "message",
        "text": "Ahh gotcha",
        "user": "U15HY5TG8",
        "ts": "1522766532.000556"
    },
    {
        "type": "message",
        "text": "so i should've betrayed",
        "user": "U15HY5TG8",
        "ts": "1522766537.000263"
    },
    {
        "type": "message",
        "text": "lol NO you should not have",
        "user": "U15HSHSS2",
        "ts": "1522766549.000304"
    },
    {
        "type": "message",
        "text": "also if you have alt accounts join on there",
        "user": "U15HSHSS2",
        "ts": "1522766560.000701"
    },
    {
        "type": "message",
        "text": "No one shall know my alt account",
        "user": "U15HY5TG8",
        "ts": "1522766573.000490"
    },
    {
        "type": "message",
        "text": "haha",
        "user": "U15HSHSS2",
        "ts": "1522766584.000418"
    },
    {
        "type": "message",
        "text": "at the end its going to reveal whos in your group",
        "user": "U15HRTAHL",
        "ts": "1522766604.000230"
    },
    {
        "type": "message",
        "text": "thats when the real CircleofTrust begins",
        "user": "U15HRTAHL",
        "ts": "1522766624.000453"
    },
    {
        "type": "message",
        "text": "Why? that doesnt make sense",
        "user": "U15HY5TG8",
        "ts": "1522766825.000579"
    },
    {
        "type": "message",
        "text": "he's kidding",
        "user": "U15HSHSS2",
        "ts": "1522766841.000041"
    },
    {
        "type": "message",
        "text": "Go join our circle Joe",
        "user": "U15HSHSS2",
        "ts": "1522766855.000556"
    },
    {
        "type": "message",
        "text": "30 days in jail and $20,000 fine",
        "user": "U15J5H60P",
        "ts": "1522776481.000389"
    },
    {
        "type": "message",
        "text": "For lying to the FBI",
        "user": "U15J5H60P",
        "ts": "1522776485.000190"
    },
    {
        "type": "message",
        "text": "Huh...",
        "user": "U15J5H60P",
        "ts": "1522776494.000578"
    },
    {
        "client_msg_id": "53CA065A-906E-4DB2-BBA6-92AF0105BCFE",
        "type": "message",
        "text": "Did you lie?",
        "user": "U15HY5TG8",
        "ts": "1522776508.000658"
    },
    {
        "type": "message",
        "text": "No",
        "user": "U15J5H60P",
        "ts": "1522776627.000695"
    },
    {
        "type": "message",
        "text": "A dutch lawyer lied to the FBI",
        "user": "U15J5H60P",
        "ts": "1522776633.000455"
    },
    {
        "type": "message",
        "text": "&gt; \"A Dutch lawyer tied to ex-Trump campaign deputy Gates gets 30 days in prison and a $20,000 fine. He admitted he lied to special counsel Mueller's team.\"",
        "user": "U15J5H60P",
        "ts": "1522776692.000701",
        "edited": {
            "user": "U15J5H60P",
            "ts": "1522776702.000000"
        }
    },
    {
        "client_msg_id": "F1D44A63-A37D-4F69-A90B-E664D06D7CA8",
        "type": "message",
        "text": "Damnnnn",
        "user": "U15HY5TG8",
        "ts": "1522776739.000049"
    },
    {
        "type": "message",
        "text": "James, your blood work come back yet?",
        "user": "U15J5H60P",
        "ts": "1522780923.000100"
    },
    {
        "type": "message",
        "text": "Turns out, Ciera cheated on you and gave you aids",
        "user": "U15J5H60P",
        "ts": "1522780981.000440"
    },
    {
        "type": "message",
        "text": ":scream:",
        "user": "U15HSHSS2",
        "ts": "1522781007.000214"
    },
    {
        "type": "message",
        "text": "aids are the worst",
        "user": "U15HRTAHL",
        "ts": "1522781008.000131"
    },
    {
        "type": "message",
        "text": "lol",
        "user": "U15HY5TG8",
        "ts": "1522781372.000480"
    },
    {
        "type": "message",
        "text": "Republicans made it rain today so we wouldn't go vote",
        "user": "U15J5H60P",
        "ts": "1522781647.000685"
    },
    {
        "type": "message",
        "text": "It's working",
        "user": "U15J5H60P",
        "ts": "1522781650.000134"
    },
    {
        "type": "message",
        "text": "lol I was thinking that too",
        "user": "U15HRTAHL",
        "ts": "1522781658.000205"
    },
    {
        "type": "message",
        "text": "Repubs are gonna win",
        "user": "U15HRTAHL",
        "ts": "1522781663.000230"
    },
    {
        "client_msg_id": "04A5BE6D-F66A-4368-B435-51506C7B2DF6",
        "type": "message",
        "text": "Lol",
        "user": "U15HY5TG8",
        "ts": "1522781827.000693"
    },
    {
        "type": "message",
        "text": "Russians*",
        "user": "U15J5H60P",
        "ts": "1522782200.000204"
    },
    {
        "client_msg_id": "98D22BD7-0D7D-441E-8769-41F97BA106EA",
        "type": "message",
        "text": "In soviet russia, elections win russians",
        "user": "U15HY5TG8",
        "ts": "1522782382.000264"
    },
    {
        "type": "message",
        "text": "Born on the First Monday,\nI am an ocean\nTwisting, turning, always under motion,\nIt's what made me breakaway\n\nRevolutions pass, and I birth many a river\nMy biggest ones total in four\nThat's where you popped up, just offshore\nDon't say I've never been a caregiver\n\nI'm easier to see in the dark, to my dismay\nBut I'm always there, even on a sunny day\nAll life pours through me, from me\nTo witness me, is to experience myself\nYour life is my life, one of many on my shelf\n\nWhat I've been trying to convey,\nI am your Atlas\nShining brighter than a festive holiday\nYou know who I am, don't be thoughtless\nIs none other than I, the _____.",
        "user": "U15HSHSS2",
        "ts": "1522786261.000170"
    },
    {
        "type": "message",
        "text": "Riddle to get into this guys circle lol",
        "user": "U15HSHSS2",
        "ts": "1522786275.000290"
    },
    {
        "type": "message",
        "text": "idk what it is...",
        "user": "U15HSHSS2",
        "ts": "1522786285.000398"
    },
    {
        "type": "message",
        "text": "How many letters?",
        "user": "U15J5H60P",
        "ts": "1522786699.000225"
    },
    {
        "type": "message",
        "text": "5?",
        "user": "U15J5H60P",
        "ts": "1522786700.000502"
    },
    {
        "type": "message",
        "text": "I don't think the dashes correspond to letters. Looks like one long underline in reddit",
        "user": "U15HSHSS2",
        "ts": "1522786739.000449"
    },
    {
        "type": "message",
        "text": "Hmm",
        "user": "U15J5H60P",
        "ts": "1522786744.000427"
    },
    {
        "type": "message",
        "text": "Moon?",
        "user": "U15J5H60P",
        "ts": "1522786748.000335"
    },
    {
        "type": "message",
        "text": "I thought it was the moon",
        "user": "U15HSHSS2",
        "ts": "1522786752.000112"
    },
    {
        "type": "message",
        "text": "nope",
        "user": "U15HSHSS2",
        "ts": "1522786753.000644"
    },
    {
        "type": "message",
        "text": "Damn",
        "user": "U15J5H60P",
        "ts": "1522786755.000522"
    },
    {
        "type": "message",
        "text": "have you googled it?",
        "user": "U15HRTAHL",
        "ts": "1522786769.000506"
    },
    {
        "type": "message",
        "text": "Fallopian tube?",
        "user": "U15J5H60P",
        "ts": "1522786771.000351"
    },
    {
        "type": "message",
        "text": "yeah",
        "user": "U15HSHSS2",
        "ts": "1522786773.000088"
    },
    {
        "type": "message",
        "text": "Garden of Eden?",
        "user": "U15J5H60P",
        "ts": "1522786987.000547"
    },
    {
        "type": "message",
        "text": "God?",
        "user": "U15J5H60P",
        "ts": "1522786988.000704"
    },
    {
        "type": "message",
        "text": "negative",
        "user": "U15HSHSS2",
        "ts": "1522787018.000086"
    },
    {
        "type": "message",
        "text": "Genesis",
        "user": "U15J5H60P",
        "ts": "1522787030.000525"
    },
    {
        "type": "message",
        "text": "India?",
        "user": "U15HRTAHL",
        "ts": "1522787066.000131"
    },
    {
        "type": "message",
        "text": "nope and nope",
        "user": "U15HSHSS2",
        "ts": "1522787097.000636"
    },
    {
        "type": "message",
        "text": "What are the oceans lol",
        "user": "U15HRTAHL",
        "ts": "1522787111.000325"
    },
    {
        "type": "message",
        "text": "Atlantic, Pacific, Indian, Arctic... what else?",
        "user": "U15HRTAHL",
        "ts": "1522787125.000584"
    },
    {
        "type": "message",
        "text": "Australia?",
        "user": "U15HRTAHL",
        "ts": "1522787182.000491"
    },
    {
        "type": "message",
        "text": "The ocean is a hypothetical",
        "user": "U15J5H60P",
        "ts": "1522787242.000174"
    },
    {
        "type": "message",
        "text": "he prefixes it with 'The' too",
        "user": "U15HSHSS2",
        "ts": "1522787252.000300"
    },
    {
        "type": "message",
        "text": "yeah I think the ocean part goes with the whole \"I'm always moving\" thing",
        "user": "U15HSHSS2",
        "ts": "1522787293.000567"
    },
    {
        "type": "message",
        "text": "light?",
        "user": "U15J5H60P",
        "ts": "1522787318.000059"
    },
    {
        "type": "message",
        "text": "tried that",
        "user": "U15HSHSS2",
        "ts": "1522787322.000099"
    },
    {
        "type": "message",
        "text": "Earth?",
        "user": "U15HRTAHL",
        "ts": "1522787323.000756"
    },
    {
        "type": "message",
        "text": "tried that too",
        "user": "U15HSHSS2",
        "ts": "1522787339.000192"
    },
    {
        "type": "message",
        "text": "rapture?",
        "user": "U15J5H60P",
        "ts": "1522787381.000249"
    },
    {
        "type": "message",
        "text": "nope",
        "user": "U15HSHSS2",
        "ts": "1522787395.000167"
    },
    {
        "type": "message",
        "text": "angel",
        "user": "U15J5H60P",
        "ts": "1522787396.000279"
    },
    {
        "type": "message",
        "text": "nada",
        "user": "U15HSHSS2",
        "ts": "1522787407.000624"
    },
    {
        "type": "message",
        "text": "God?",
        "user": "U15J5H60P",
        "ts": "1522787439.000397"
    },
    {
        "type": "message",
        "text": "almighty?",
        "user": "U15J5H60P",
        "ts": "1522787444.000608"
    },
    {
        "type": "message",
        "text": "did you try world?",
        "user": "U15HRTAHL",
        "ts": "1522787540.000554"
    },
    {
        "type": "message",
        "text": "yup",
        "user": "U15HSHSS2",
        "ts": "1522787552.000255"
    },
    {
        "type": "message",
        "text": "Did you try almighty?",
        "user": "U15J5H60P",
        "ts": "1522787559.000458"
    },
    {
        "type": "message",
        "text": "yeah",
        "user": "U15HSHSS2",
        "ts": "1522787564.000392"
    },
    {
        "type": "message",
        "text": "air?",
        "user": "U15J5H60P",
        "ts": "1522787638.000395"
    },
    {
        "type": "message",
        "text": "Wind?",
        "user": "U15J5H60P",
        "ts": "1522787639.000651"
    },
    {
        "type": "message",
        "text": "nope nope",
        "user": "U15HSHSS2",
        "ts": "1522787662.000139"
    },
    {
        "type": "message",
        "text": "ffs",
        "user": "U15J5H60P",
        "ts": "1522787665.000507"
    },
    {
        "type": "message",
        "text": "void",
        "user": "U15J5H60P",
        "ts": "1522787684.000599"
    },
    {
        "type": "message",
        "text": "space",
        "user": "U15J5H60P",
        "ts": "1522787692.000538"
    },
    {
        "type": "message",
        "text": "stars",
        "user": "U15J5H60P",
        "ts": "1522787694.000020"
    },
    {
        "type": "message",
        "text": "nopee",
        "user": "U15HSHSS2",
        "ts": "1522787714.000320"
    },
    {
        "type": "message",
        "text": "Elements",
        "user": "U15HRTAHL",
        "ts": "1522787861.000260"
    },
    {
        "type": "message",
        "text": "Atlantis?",
        "user": "U15J5H60P",
        "ts": "1522788225.000534"
    },
    {
        "type": "message",
        "text": "Heaven",
        "user": "U15J5H60P",
        "ts": "1522788331.000240"
    },
    {
        "type": "message",
        "text": "Can I have a link so I can try it?",
        "user": "U15J5H60P",
        "ts": "1522788336.000474"
    },
    {
        "type": "message",
        "text": "omfg",
        "user": "U15HSHSS2",
        "ts": "1522788339.000081"
    },
    {
        "type": "message",
        "text": "he's solved it",
        "user": "U15HRTAHL",
        "ts": "1522788346.000521"
    },
    {
        "type": "message",
        "text": "dumb fuck didn't make the answer the key",
        "user": "U15HSHSS2",
        "ts": "1522788347.000304"
    },
    {
        "type": "message",
        "text": "No fucking shit",
        "user": "U15J5H60P",
        "ts": "1522788353.000556"
    },
    {
        "type": "message",
        "text": "your supposed to PM him the answer",
        "user": "U15HSHSS2",
        "ts": "1522788361.000275"
    },
    {
        "type": "message",
        "text": "....",
        "user": "U15HRTAHL",
        "ts": "1522788364.000389"
    },
    {
        "type": "message",
        "text": "and he gives you the key",
        "user": "U15HSHSS2",
        "ts": "1522788367.000336"
    },
    {
        "type": "message",
        "text": "FFS",
        "user": "U15J5H60P",
        "ts": "1522788368.000044"
    },
    {
        "type": "message",
        "text": "FFS",
        "user": "U15J5H60P",
        "ts": "1522788371.000574"
    },
    {
        "type": "message",
        "text": "FFS",
        "user": "U15J5H60P",
        "ts": "1522788373.000014"
    },
    {
        "type": "message",
        "text": "FFS",
        "user": "U15J5H60P",
        "ts": "1522788374.000079"
    },
    {
        "type": "message",
        "text": "FFS",
        "user": "U15J5H60P",
        "ts": "1522788375.000584"
    },
    {
        "client_msg_id": "A5C89092-AA9C-4F18-80DF-31B59194705F",
        "type": "message",
        "text": "Enough",
        "user": "U15HY5TG8",
        "ts": "1522788380.000383"
    },
    {
        "type": "message",
        "text": "I posted this to the company slack to solve",
        "user": "U15J5H60P",
        "ts": "1522788389.000066"
    },
    {
        "type": "message",
        "text": "And turns out we probably already have the answer",
        "user": "U15J5H60P",
        "ts": "1522788398.000220"
    },
    {
        "type": "message",
        "text": "Now you look like an idiot",
        "user": "U15HRTAHL",
        "ts": "1522788403.000472"
    },
    {
        "type": "message",
        "text": "Ffs",
        "user": "U15J5H60P",
        "ts": "1522788408.000592"
    },
    {
        "type": "message",
        "text": "lol",
        "user": "U15HSHSS2",
        "ts": "1522788435.000664"
    },
    {
        "client_msg_id": "E249780D-167D-415C-8F54-0046D57E6AAA",
        "type": "message",
        "text": "Lol",
        "user": "U15HY5TG8",
        "ts": "1522788436.000514"
    },
    {
        "type": "message",
        "text": "so what was the answer",
        "user": "U15HRTAHL",
        "ts": "1522788444.000033"
    },
    {
        "type": "message",
        "text": "I don't fucking know lol",
        "user": "U15HSHSS2",
        "ts": "1522788455.000486"
    },
    {
        "type": "message",
        "text": "probably moon",
        "user": "U15HSHSS2",
        "ts": "1522788460.000200"
    },
    {
        "type": "message",
        "text": "or stars",
        "user": "U15HSHSS2",
        "ts": "1522788461.000493"
    },
    {
        "type": "message",
        "text": "Shooting at YouTube",
        "user": "U15J5H60P",
        "ts": "1522789679.000091"
    },
    {
        "type": "message",
        "text": "they shoot videos",
        "user": "U15HRTAHL",
        "ts": "1522789699.000240"
    },
    {
        "type": "message",
        "text": "shootings happen all the time there",
        "user": "U15HRTAHL",
        "ts": "1522789705.000280"
    },
    {
        "type": "message",
        "text": "lol",
        "user": "U15HSHSS2",
        "ts": "1522789729.000107"
    },
    {
        "type": "message",
        "text": "That kid has made 2k on his pb kick starter",
        "user": "U15HRTAHL",
        "ts": "1522790725.000222"
    },
    {
        "type": "message",
        "text": "maybe I'm doing life wrong",
        "user": "U15HRTAHL",
        "ts": "1522790732.000101"
    },
    {
        "type": "message",
        "text": "you guys wanna make a water company?",
        "user": "U15HRTAHL",
        "ts": "1522790739.000346"
    },
    {
        "type": "message",
        "text": "we can just use our tap water and add some shit to it",
        "user": "U15HRTAHL",
        "ts": "1522790751.000380"
    },
    {
        "client_msg_id": "B177B146-5C3F-4827-B39C-BCE69322930A",
        "type": "message",
        "text": "Raw water",
        "user": "U15J5H60P",
        "ts": "1522790988.000075"
    },
    {
        "client_msg_id": "1CB5A340-DF28-4E98-AA54-3EA9B26D5F32",
        "type": "message",
        "text": "Sell it right on the beach at Bradford",
        "user": "U15J5H60P",
        "ts": "1522790997.000497"
    },
    {
        "client_msg_id": "04C2C96A-88CF-4977-A659-644BD4BF9A61",
        "type": "message",
        "text": "Organic or regular? Regular we'll scoop it out of the waves ($6). Organic, we'll find some still water with algae and scoop some raw water out.($7)",
        "user": "U15J5H60P",
        "ts": "1522791075.000551"
    },
    {
        "client_msg_id": "7FC90770-0C8F-4EF2-92F3-7D254F38F238",
        "type": "message",
        "text": "I wrote all of us in",
        "user": "U15J5H60P",
        "ts": "1522795370.000069"
    },
    {
        "client_msg_id": "91D60F44-0872-47BA-BFBC-1624AA14C7E1",
        "type": "message",
        "text": "Against unopposed people",
        "user": "U15J5H60P",
        "ts": "1522795384.000142"
    },
    {
        "client_msg_id": "9124d731-b2e7-4fe2-9a03-3b91da8a0970",
        "type": "message",
        "text": "Dallet won in a landslide",
        "user": "U15HRTAHL",
        "ts": "1522809903.000193"
    },
    {
        "client_msg_id": "f5c28396-c585-4efe-841c-a8ce44dabede",
        "type": "message",
        "text": "Oh baby",
        "user": "U15HRTAHL",
        "ts": "1522809907.000150"
    },
    {
        "client_msg_id": "551461D6-59B4-4D64-9BC2-AF20ED830DAC",
        "type": "message",
        "text": "Wooooo!",
        "user": "U15J5H60P",
        "ts": "1522809914.000075"
    },
    {
        "client_msg_id": "8C1CB019-B9E0-42BB-AD08-53CC009BAEE7",
        "type": "message",
        "text": "My vote counted!!",
        "user": "U15J5H60P",
        "ts": "1522809921.000084"
    },
    {
        "client_msg_id": "D93628FB-240E-4334-81EC-B07282B0BCD7",
        "type": "message",
        "text": "I wrote you in for one Joe",
        "user": "U15J5H60P",
        "ts": "1522809938.000026"
    },
    {
        "client_msg_id": "49ED4E47-5B6B-4293-BD75-8E4E0F4CE630",
        "type": "message",
        "text": "I assume thats the dem?",
        "user": "U15HY5TG8",
        "ts": "1522809940.000130"
    },
    {
        "client_msg_id": "947C1B29-091F-4DC6-B6E1-9EC2AF7EA4A9",
        "type": "message",
        "text": "And we're keeping the treasurer",
        "user": "U15J5H60P",
        "ts": "1522809993.000041"
    },
    {
        "client_msg_id": "4A0658B7-082A-4925-B348-6180A26F98BB",
        "type": "message",
        "text": "Was I supposed to vote yes or no?",
        "user": "U15J5H60P",
        "ts": "1522809999.000259"
    },
    {
        "client_msg_id": "d7acaa72-d8d0-4141-8143-0ab9844726e4",
        "type": "message",
        "text": "Vote no.",
        "user": "U15HRTAHL",
        "ts": "1522810248.000042"
    },
    {
        "client_msg_id": "115a3cd5-e272-45c4-99f7-7be16addb5ce",
        "type": "message",
        "text": "So we're good",
        "user": "U15HRTAHL",
        "ts": "1522810254.000010"
    },
    {
        "client_msg_id": "99cdf6eb-9584-4023-af48-59e62c7592e2",
        "type": "message",
        "text": "We're reclaiming this state",
        "user": "U15HRTAHL",
        "ts": "1522810259.000200"
    },
    {
        "client_msg_id": "4156a2d8-c9e5-498a-8e69-f768109580e7",
        "type": "message",
        "text": "Walker is next",
        "user": "U15HRTAHL",
        "ts": "1522810263.000129"
    },
    {
        "client_msg_id": "e0ec6f55-cee8-4034-b1ba-2e47401f1ed7",
        "type": "message",
        "text": "Then trump",
        "user": "U15HRTAHL",
        "ts": "1522810269.000151"
    },
    {
        "client_msg_id": "32a04220-446c-430b-a510-cef5a0c5d9e0",
        "type": "message",
        "text": "Then Johnson",
        "user": "U15HRTAHL",
        "ts": "1522810273.000002"
    },
    {
        "client_msg_id": "ED4E55B3-4CC1-428E-A8B8-2B511C07915D",
        "type": "message",
        "text": "I want Ryan gone",
        "user": "U15J5H60P",
        "ts": "1522811027.000233"
    }
]