[
    {
        "client_msg_id": "fb4ec1ca-0e33-4fec-9a9a-116b49806d60",
        "type": "message",
        "text": "I can't sleep",
        "user": "U15HRTAHL",
        "ts": "1525944439.000314"
    },
    {
        "client_msg_id": "79a7d668-4702-47e7-9d14-1d8ab8159f97",
        "type": "message",
        "text": "Been up since 2:30",
        "user": "U15HRTAHL",
        "ts": "1525944471.000329"
    },
    {
        "client_msg_id": "FD311942-6B75-47EB-B895-A3ABCEB1BEC5",
        "type": "message",
        "text": "Damn...",
        "user": "U15HSHSS2",
        "ts": "1525947426.000049"
    },
    {
        "client_msg_id": "51B7175E-4806-47B7-AFA6-10117F47B70D",
        "type": "message",
        "text": "Watch some ASMR",
        "user": "U15HSHSS2",
        "ts": "1525947438.000084"
    },
    {
        "client_msg_id": "7915312b-ac83-4455-bcd8-d4d603447836",
        "type": "message",
        "text": "I guess I'll just sleep really good tonight",
        "user": "U15HRTAHL",
        "ts": "1525948046.000301"
    },
    {
        "type": "message",
        "text": "Ah dang",
        "user": "U15J5H60P",
        "ts": "1525956496.000045"
    },
    {
        "client_msg_id": "D34E235C-BECE-4A59-9051-7302E0F4AB4F",
        "type": "message",
        "text": "Off to Texas :sunglasses:",
        "user": "U15HSHSS2",
        "ts": "1525958342.000301"
    },
    {
        "client_msg_id": "214af7d9-4769-40f4-a472-202335de7ae1",
        "type": "message",
        "text": "For what?",
        "user": "U15HRTAHL",
        "ts": "1525958459.000289"
    },
    {
        "type": "message",
        "text": "Wooo!",
        "user": "U15J5H60P",
        "ts": "1525958785.000348"
    },
    {
        "type": "message",
        "text": "For what?",
        "user": "U15J5H60P",
        "ts": "1525958786.000624"
    },
    {
        "client_msg_id": "B031C0F9-8BC8-4A32-9860-CB22A5003A4E",
        "type": "message",
        "text": "Going to see some of lakshmis family",
        "user": "U15HSHSS2",
        "ts": "1525960080.000018"
    },
    {
        "type": "message",
        "text": "Nice!",
        "user": "U15J5H60P",
        "ts": "1525960884.000578",
        "edited": {
            "user": "U15J5H60P",
            "ts": "1525960891.000000"
        }
    },
    {
        "client_msg_id": "baa026cd-d6fd-4a7e-9d8c-f9ac571ade07",
        "type": "message",
        "text": "Saweeet",
        "user": "U15HRTAHL",
        "ts": "1525961268.000011"
    },
    {
        "client_msg_id": "c8525f04-9960-4726-b229-564bcad56bc2",
        "type": "message",
        "text": "Where in Texas?",
        "user": "U15HRTAHL",
        "ts": "1525961272.000406"
    },
    {
        "client_msg_id": "fef5ee7d-c482-4af8-8b60-222949514271",
        "type": "message",
        "text": "It's a big state",
        "user": "U15HRTAHL",
        "ts": "1525961276.000499"
    },
    {
        "client_msg_id": "AC345D6A-481D-429D-BC6A-3ABE837255EF",
        "type": "message",
        "text": "Dallas",
        "user": "U15HSHSS2",
        "ts": "1525963502.000397"
    },
    {
        "client_msg_id": "4F4D4565-FD79-4510-8D11-95B044F5E5B9",
        "type": "message",
        "text": "My Uwm account was turned off today :sob:",
        "user": "U15HZ01QX",
        "ts": "1525963766.000504"
    },
    {
        "client_msg_id": "DCA886DA-3194-403C-9C6A-D0222AB6F3FF",
        "type": "message",
        "text": "Sad day",
        "user": "U15HSHSS2",
        "ts": "1525963961.000730"
    },
    {
        "client_msg_id": "DFFD30C8-F28F-448D-8F7A-8212CB7EB4D4",
        "type": "message",
        "text": "Did they tell you that?",
        "user": "U15HY5TG8",
        "ts": "1525964332.000893"
    },
    {
        "client_msg_id": "5A324B6B-8458-4223-BBB2-80ACF0CFE8F5",
        "type": "message",
        "text": "Oooo i just got promoted for my password too haha",
        "user": "U15HY5TG8",
        "ts": "1525964358.000432"
    },
    {
        "client_msg_id": "89735CFE-A4B4-4A47-8A68-2C17F8D3E377",
        "type": "message",
        "text": "Prompted*",
        "user": "U15HY5TG8",
        "ts": "1525964373.000011"
    },
    {
        "client_msg_id": "A9FA6632-6345-4AE7-9BC0-F96ACEFFB126",
        "type": "message",
        "text": "\nLol they emailed 3 weeks ago saying it was going away",
        "user": "U15HZ01QX",
        "ts": "1525964373.000165"
    },
    {
        "client_msg_id": "46D2C469-6DDF-4AE4-932A-F35181E21EF2",
        "type": "message",
        "text": "And the password prompts have been buggin me lol",
        "user": "U15HZ01QX",
        "ts": "1525964383.000226"
    },
    {
        "client_msg_id": "E239FD19-C78E-4190-8A1D-44EBDAE19F66",
        "type": "message",
        "text": "Lol yeah. Bittersweet though",
        "user": "U15HY5TG8",
        "ts": "1525964398.000576"
    },
    {
        "client_msg_id": "35F46B4F-544D-432D-A11A-6D1D857FBDC3",
        "type": "message",
        "text": "Should cut down on spam i think",
        "user": "U15HY5TG8",
        "ts": "1525964419.000659"
    },
    {
        "type": "message",
        "text": "HA!",
        "user": "U15J5H60P",
        "ts": "1525967518.000618"
    },
    {
        "type": "message",
        "text": "I JUST COPPED A SPOT AT WORK FOR PARKING",
        "user": "U15J5H60P",
        "ts": "1525967526.000280"
    },
    {
        "type": "message",
        "text": "for free?",
        "user": "U15HRTAHL",
        "ts": "1525967547.000723"
    },
    {
        "type": "message",
        "text": "lol No",
        "user": "U15J5H60P",
        "ts": "1525967576.000238"
    },
    {
        "type": "message",
        "text": "$130\/month pre-tax",
        "user": "U15J5H60P",
        "ts": "1525967586.000157"
    },
    {
        "type": "message",
        "text": "BUT",
        "user": "U15J5H60P",
        "ts": "1525967589.000359"
    },
    {
        "type": "message",
        "text": "People usually have to wait ~10 years to get a spot",
        "user": "U15J5H60P",
        "ts": "1525967608.000668"
    },
    {
        "type": "message",
        "text": "I mistakenly got sent an email",
        "user": "U15J5H60P",
        "ts": "1525967615.000601"
    },
    {
        "type": "message",
        "text": "I signed up",
        "user": "U15J5H60P",
        "ts": "1525967620.000161"
    },
    {
        "type": "message",
        "text": "must be nice being asian",
        "user": "U15HRTAHL",
        "ts": "1525967624.000131"
    },
    {
        "client_msg_id": "76594169-B3D1-4B15-8D17-00173982C3FC",
        "type": "message",
        "text": "Can’t you just use one of the downtown lots",
        "user": "U15HZ01QX",
        "ts": "1525967625.000573"
    },
    {
        "client_msg_id": "827AC3AC-BAAA-4B21-A35C-43C0200E55DE",
        "type": "message",
        "text": "Like the third ward ones can’t be that expensive ",
        "user": "U15HZ01QX",
        "ts": "1525967638.000328"
    },
    {
        "type": "message",
        "text": "$8\/day post tax at O'Donnell which I used to park in during the winter",
        "user": "U15J5H60P",
        "ts": "1525967677.000778"
    },
    {
        "type": "message",
        "text": "Anyways, I got an email saying that the email was by mistake to 150 people, but whoever signed up wouldn't be taken off",
        "user": "U15J5H60P",
        "ts": "1525967735.000694"
    },
    {
        "type": "message",
        "text": "I signed up because I know I'm moving out of the city",
        "user": "U15J5H60P",
        "ts": "1525967749.000057"
    },
    {
        "type": "message",
        "text": "When? Didn't you resign your lease?",
        "user": "U15HRTAHL",
        "ts": "1525967764.000371"
    },
    {
        "type": "message",
        "text": "Yeah",
        "user": "U15J5H60P",
        "ts": "1525967795.000845"
    },
    {
        "type": "message",
        "text": "I'll probably be moving out next year though",
        "user": "U15J5H60P",
        "ts": "1525967804.000085"
    },
    {
        "type": "message",
        "text": "But if I didn't get it now, I would have to wait another 8 years",
        "user": "U15J5H60P",
        "ts": "1525967821.000356"
    },
    {
        "type": "message",
        "text": "yeah fak that",
        "user": "U15HRTAHL",
        "ts": "1525968117.000038"
    },
    {
        "client_msg_id": "bd940497-83a2-4cae-80fa-4622feea798a",
        "type": "message",
        "text": "Well boys. I accepted a new offer",
        "user": "U15HRTAHL",
        "ts": "1525988996.000111"
    },
    {
        "client_msg_id": "0776B023-A120-48F3-8F25-9420DF989AD6",
        "type": "message",
        "text": "Yayayayay!!!",
        "user": "U15J5H60P",
        "ts": "1525989003.000211"
    },
    {
        "client_msg_id": "7539A29B-BE2D-4FA5-A9B7-25B20128FAC9",
        "type": "message",
        "text": "You'll have to let us know how PKWare is!",
        "user": "U15J5H60P",
        "ts": "1525989013.000105"
    },
    {
        "client_msg_id": "62120a59-0176-4fb0-9008-b046e106164e",
        "type": "message",
        "text": "How'd ya know it was pkware?",
        "user": "U15HRTAHL",
        "ts": "1525989028.000245"
    },
    {
        "client_msg_id": "0CF1803B-B8B3-4DDD-B022-A4D0FA8B2688",
        "type": "message",
        "text": "Amazon!! ",
        "user": "U15HZ01QX",
        "ts": "1525989038.000073"
    },
    {
        "client_msg_id": "952A8A98-C1FE-4748-961B-BD38302C3F25",
        "type": "message",
        "text": "You’re outta here!!",
        "user": "U15HZ01QX",
        "ts": "1525989043.000325"
    },
    {
        "client_msg_id": "9A7085E0-E109-4337-B678-8385A0606DE5",
        "type": "message",
        "text": "Cause you submitted a counter offwe",
        "user": "U15J5H60P",
        "ts": "1525989048.000084"
    },
    {
        "client_msg_id": "B200B162-73E1-481D-B49F-14E5E83EF41C",
        "type": "message",
        "text": "Also, they offered you $110k to start with so",
        "user": "U15J5H60P",
        "ts": "1525989061.000343"
    },
    {
        "client_msg_id": "8C2DC894-7020-45CF-AA08-D8A0BFB7AEDC",
        "type": "message",
        "text": "Congrats joe! ",
        "user": "U15HZ01QX",
        "ts": "1525989064.000241"
    },
    {
        "client_msg_id": "B6E57F0D-E1A0-43F9-B653-6920B892B847",
        "type": "message",
        "text": "Killin it!",
        "user": "U15J5H60P",
        "ts": "1525989075.000420"
    },
    {
        "client_msg_id": "34200B49-A5A8-48C1-B4A6-8E2E67AEB52D",
        "type": "message",
        "text": "When're you taking us out for drinks?",
        "user": "U15J5H60P",
        "ts": "1525989275.000231"
    },
    {
        "client_msg_id": "CFEADFBC-BFB5-4FD9-9D61-68C6AA487352",
        "type": "message",
        "text": "Didn't you say something about taking us out when you get a new job?",
        "user": "U15J5H60P",
        "ts": "1525989291.000374"
    },
    {
        "client_msg_id": "197FD3D8-AD8A-4E3E-A508-E44026155F29",
        "type": "message",
        "text": "Now you can get God of War!!",
        "user": "U15J5H60P",
        "ts": "1525989345.000012"
    },
    {
        "client_msg_id": "37270e8d-2f4d-4fb4-a327-aa1c6d3d4267",
        "type": "message",
        "text": "Amazon denied me",
        "user": "U15HRTAHL",
        "ts": "1525990531.000067"
    },
    {
        "client_msg_id": "4286FBC9-719A-4D9D-A0AC-363294A4DC54",
        "type": "message",
        "text": "Boooooooo",
        "user": "U15J5H60P",
        "ts": "1525990555.000020"
    },
    {
        "client_msg_id": "15170B4D-0685-4D02-8C8C-E1AC241B0431",
        "type": "message",
        "text": "Did they give you any feedback?",
        "user": "U15J5H60P",
        "ts": "1525990590.000099"
    },
    {
        "type": "message",
        "text": "I sent back \"Matthew and I.\"",
        "files": [
            {
                "id": "FAMQUK62F",
                "created": 1525990992,
                "timestamp": 1525990992,
                "name": "Screenshot_20180510-172233.png",
                "title": "Screenshot_20180510-172233.png",
                "mimetype": "image\/png",
                "filetype": "png",
                "pretty_type": "PNG",
                "user": "U15HRTAHL",
                "editable": false,
                "size": 173535,
                "mode": "hosted",
                "is_external": false,
                "external_type": "",
                "is_public": true,
                "public_url_shared": false,
                "display_as_bot": false,
                "username": "",
                "url_private": "https:\/\/files.slack.com\/files-pri\/T15HR7G14-FAMQUK62F\/screenshot_20180510-172233.png?t=xoxe-39603254038-632282913120-620827978611-790c09c056a65e291519f1f9c44516dc",
                "url_private_download": "https:\/\/files.slack.com\/files-pri\/T15HR7G14-FAMQUK62F\/download\/screenshot_20180510-172233.png?t=xoxe-39603254038-632282913120-620827978611-790c09c056a65e291519f1f9c44516dc",
                "thumb_64": "https:\/\/files.slack.com\/files-tmb\/T15HR7G14-FAMQUK62F-12fa59cd99\/screenshot_20180510-172233_64.png?t=xoxe-39603254038-632282913120-620827978611-790c09c056a65e291519f1f9c44516dc",
                "thumb_80": "https:\/\/files.slack.com\/files-tmb\/T15HR7G14-FAMQUK62F-12fa59cd99\/screenshot_20180510-172233_80.png?t=xoxe-39603254038-632282913120-620827978611-790c09c056a65e291519f1f9c44516dc",
                "thumb_360": "https:\/\/files.slack.com\/files-tmb\/T15HR7G14-FAMQUK62F-12fa59cd99\/screenshot_20180510-172233_360.png?t=xoxe-39603254038-632282913120-620827978611-790c09c056a65e291519f1f9c44516dc",
                "thumb_360_w": 203,
                "thumb_360_h": 360,
                "thumb_480": "https:\/\/files.slack.com\/files-tmb\/T15HR7G14-FAMQUK62F-12fa59cd99\/screenshot_20180510-172233_480.png?t=xoxe-39603254038-632282913120-620827978611-790c09c056a65e291519f1f9c44516dc",
                "thumb_480_w": 270,
                "thumb_480_h": 480,
                "thumb_160": "https:\/\/files.slack.com\/files-tmb\/T15HR7G14-FAMQUK62F-12fa59cd99\/screenshot_20180510-172233_160.png?t=xoxe-39603254038-632282913120-620827978611-790c09c056a65e291519f1f9c44516dc",
                "thumb_720": "https:\/\/files.slack.com\/files-tmb\/T15HR7G14-FAMQUK62F-12fa59cd99\/screenshot_20180510-172233_720.png?t=xoxe-39603254038-632282913120-620827978611-790c09c056a65e291519f1f9c44516dc",
                "thumb_720_w": 405,
                "thumb_720_h": 720,
                "thumb_800": "https:\/\/files.slack.com\/files-tmb\/T15HR7G14-FAMQUK62F-12fa59cd99\/screenshot_20180510-172233_800.png?t=xoxe-39603254038-632282913120-620827978611-790c09c056a65e291519f1f9c44516dc",
                "thumb_800_w": 800,
                "thumb_800_h": 1422,
                "thumb_960": "https:\/\/files.slack.com\/files-tmb\/T15HR7G14-FAMQUK62F-12fa59cd99\/screenshot_20180510-172233_960.png?t=xoxe-39603254038-632282913120-620827978611-790c09c056a65e291519f1f9c44516dc",
                "thumb_960_w": 540,
                "thumb_960_h": 960,
                "thumb_1024": "https:\/\/files.slack.com\/files-tmb\/T15HR7G14-FAMQUK62F-12fa59cd99\/screenshot_20180510-172233_1024.png?t=xoxe-39603254038-632282913120-620827978611-790c09c056a65e291519f1f9c44516dc",
                "thumb_1024_w": 576,
                "thumb_1024_h": 1024,
                "image_exif_rotation": 1,
                "original_w": 1440,
                "original_h": 2560,
                "permalink": "https:\/\/freeuwmke.slack.com\/files\/U15HRTAHL\/FAMQUK62F\/screenshot_20180510-172233.png",
                "permalink_public": "https:\/\/slack-files.com\/T15HR7G14-FAMQUK62F-3d3142ff62",
                "has_rich_preview": false
            }
        ],
        "upload": true,
        "user": "U15HRTAHL",
        "display_as_bot": false,
        "ts": "1525990995.000369"
    },
    {
        "type": "message",
        "text": "lololololol",
        "user": "U15J5H60P",
        "ts": "1525991413.000117"
    },
    {
        "client_msg_id": "15E6594B-0E91-46CC-97E1-E24B1B26451D",
        "type": "message",
        "text": "Hahah",
        "user": "U15HSHSS2",
        "ts": "1525991807.000215"
    },
    {
        "client_msg_id": "72FF87AB-4C67-4119-9B54-652C6BCE5B16",
        "type": "message",
        "text": "Niccee though!",
        "user": "U15HSHSS2",
        "ts": "1525991831.000216"
    },
    {
        "client_msg_id": "7CACC325-E3E0-4FFF-B37D-5E29A6DAD76F",
        "type": "message",
        "text": "Sales force stuff at pkware too? I forgot",
        "user": "U15HSHSS2",
        "ts": "1525991853.000201"
    },
    {
        "client_msg_id": "6502439a-844e-439b-9987-91085e2f35f6",
        "type": "message",
        "text": "Lol I didn't actually send it but yeah. My title is technically Internal Software Engineer. Ill be doing Salesforce stuff and some azure stuff",
        "user": "U15HRTAHL",
        "ts": "1525992589.000300"
    },
    {
        "client_msg_id": "AF5C78D4-E225-4EA5-8C9E-8D5F538FCD06",
        "type": "message",
        "text": "I still have mixed feelings with \"me and matthew\" vs \"matthew and I\" because the latter is suuposed to make sense if you just replace it with \"I\"....which it wouldnt",
        "user": "U15HY5TG8",
        "ts": "1526010421.000131"
    },
    {
        "client_msg_id": "75075FF9-90AA-42B9-930E-6105CBB18B8A",
        "type": "message",
        "text": "Where y’all attt",
        "user": "U15HSHSS2",
        "ts": "1526014691.000161"
    },
    {
        "client_msg_id": "4E419E45-3072-44CD-8B68-A0B9513603B3",
        "type": "message",
        "text": "Come to dallasss",
        "user": "U15HSHSS2",
        "ts": "1526014696.000051"
    }
]