[
    {
        "client_msg_id": "B6DE26A0-6C35-4B44-AE3A-BF53C400868F",
        "type": "message",
        "text": "Our friend Andy is having a birthday party but I’m almost 100% that the party is exactly the one we did last year lol",
        "user": "U15HZ01QX",
        "ts": "1520349594.000005"
    },
    {
        "type": "message",
        "text": "happy birthday <@U15J5H60P>. I didn't know you were going by Andy now",
        "user": "U15HRTAHL",
        "ts": "1520349839.000639"
    },
    {
        "type": "message",
        "text": "lol",
        "user": "U15J5H60P",
        "ts": "1520349892.000773"
    },
    {
        "type": "message",
        "text": "or that your bday changed",
        "user": "U15HRTAHL",
        "ts": "1520349895.000110"
    },
    {
        "type": "message",
        "text": "voter fraud",
        "user": "U15HRTAHL",
        "ts": "1520349899.000784"
    },
    {
        "type": "message",
        "text": "I was born again",
        "user": "U15J5H60P",
        "ts": "1520349902.000039"
    },
    {
        "type": "message",
        "text": "I'm a god",
        "user": "U15J5H60P",
        "ts": "1520349903.000756"
    },
    {
        "client_msg_id": "853AC755-5785-4EA9-99F9-C903AA5E68E8",
        "type": "message",
        "text": "Jesus*",
        "user": "U15HZ01QX",
        "ts": "1520349911.000504"
    },
    {
        "type": "message",
        "text": "No, Jesus is dumb.",
        "user": "U15J5H60P",
        "ts": "1520349978.000661"
    },
    {
        "type": "message",
        "text": "He's a fraud",
        "user": "U15J5H60P",
        "ts": "1520349986.000081"
    },
    {
        "type": "message",
        "text": "I'm the real deal. Only Gods can be born again",
        "user": "U15J5H60P",
        "ts": "1520349994.000001"
    },
    {
        "client_msg_id": "FF67AD62-B621-41DE-8FD8-813C7D775EB1",
        "type": "message",
        "text": "God wasn’t born again",
        "user": "U15HZ01QX",
        "ts": "1520349996.000157"
    },
    {
        "client_msg_id": "9E3F4AF9-7331-4C48-AFA6-C59EFADDB258",
        "type": "message",
        "text": "Jesus was",
        "user": "U15HZ01QX",
        "ts": "1520350000.000219"
    },
    {
        "type": "message",
        "text": "Yeah, your god wasn't.",
        "user": "U15J5H60P",
        "ts": "1520350005.000384"
    },
    {
        "client_msg_id": "C5B36B25-3530-44E3-9388-83CFB07AD7BA",
        "type": "message",
        "text": "You’re a Jesus",
        "user": "U15HZ01QX",
        "ts": "1520350008.000439"
    },
    {
        "client_msg_id": "F280B093-7A9B-4F92-818B-FE93BF4398FF",
        "type": "message",
        "text": "No god was",
        "user": "U15HZ01QX",
        "ts": "1520350011.000520"
    },
    {
        "type": "message",
        "text": "I was",
        "user": "U15J5H60P",
        "ts": "1520350017.000883"
    },
    {
        "type": "message",
        "text": "So I am the god of rebirth.",
        "user": "U15J5H60P",
        "ts": "1520350027.000411"
    },
    {
        "type": "message",
        "text": "Duh",
        "user": "U15J5H60P",
        "ts": "1520350033.000770"
    },
    {
        "type": "message",
        "text": "God",
        "user": "U15J5H60P",
        "ts": "1520350034.000765"
    },
    {
        "client_msg_id": "A6AFC500-A211-4001-B0EC-2AB361CC014F",
        "type": "message",
        "text": ":sneezing_face:",
        "user": "U15HZ01QX",
        "ts": "1520350057.000484"
    },
    {
        "type": "message",
        "text": "Get your deities right",
        "user": "U15J5H60P",
        "ts": "1520350065.000459"
    },
    {
        "type": "message",
        "text": "lol i go to ask the devs a question",
        "user": "U15HZ01QX",
        "ts": "1520350284.000444"
    },
    {
        "type": "message",
        "text": "",
        "files": [
            {
                "id": "F9KBB9Z42",
                "created": 1520350288,
                "timestamp": 1520350288,
                "name": "image.png",
                "title": "image.png",
                "mimetype": "image\/png",
                "filetype": "png",
                "pretty_type": "PNG",
                "user": "U15HZ01QX",
                "editable": false,
                "size": 23027,
                "mode": "hosted",
                "is_external": false,
                "external_type": "",
                "is_public": true,
                "public_url_shared": false,
                "display_as_bot": false,
                "username": "",
                "url_private": "https:\/\/files.slack.com\/files-pri\/T15HR7G14-F9KBB9Z42\/image.png?t=xoxe-39603254038-632282913120-620827978611-790c09c056a65e291519f1f9c44516dc",
                "url_private_download": "https:\/\/files.slack.com\/files-pri\/T15HR7G14-F9KBB9Z42\/download\/image.png?t=xoxe-39603254038-632282913120-620827978611-790c09c056a65e291519f1f9c44516dc",
                "thumb_64": "https:\/\/files.slack.com\/files-tmb\/T15HR7G14-F9KBB9Z42-eda1cd5258\/image_64.png?t=xoxe-39603254038-632282913120-620827978611-790c09c056a65e291519f1f9c44516dc",
                "thumb_80": "https:\/\/files.slack.com\/files-tmb\/T15HR7G14-F9KBB9Z42-eda1cd5258\/image_80.png?t=xoxe-39603254038-632282913120-620827978611-790c09c056a65e291519f1f9c44516dc",
                "thumb_360": "https:\/\/files.slack.com\/files-tmb\/T15HR7G14-F9KBB9Z42-eda1cd5258\/image_360.png?t=xoxe-39603254038-632282913120-620827978611-790c09c056a65e291519f1f9c44516dc",
                "thumb_360_w": 360,
                "thumb_360_h": 113,
                "thumb_480": "https:\/\/files.slack.com\/files-tmb\/T15HR7G14-F9KBB9Z42-eda1cd5258\/image_480.png?t=xoxe-39603254038-632282913120-620827978611-790c09c056a65e291519f1f9c44516dc",
                "thumb_480_w": 480,
                "thumb_480_h": 150,
                "thumb_160": "https:\/\/files.slack.com\/files-tmb\/T15HR7G14-F9KBB9Z42-eda1cd5258\/image_160.png?t=xoxe-39603254038-632282913120-620827978611-790c09c056a65e291519f1f9c44516dc",
                "image_exif_rotation": 1,
                "original_w": 536,
                "original_h": 168,
                "permalink": "https:\/\/freeuwmke.slack.com\/files\/U15HZ01QX\/F9KBB9Z42\/image.png",
                "permalink_public": "https:\/\/slack-files.com\/T15HR7G14-F9KBB9Z42-cce62eb83d",
                "has_rich_preview": false
            }
        ],
        "upload": true,
        "user": "U15HZ01QX",
        "display_as_bot": false,
        "ts": "1520350289.000551"
    },
    {
        "client_msg_id": "677E4CAB-33A5-4024-BE27-106858623159",
        "type": "message",
        "text": "Lol",
        "user": "U15HY5TG8",
        "ts": "1520350367.000119"
    },
    {
        "type": "message",
        "text": "Is that the story?",
        "user": "U15HRTAHL",
        "ts": "1520350431.000835"
    },
    {
        "type": "message",
        "text": "As in, \"fuck off, just send me a message\"",
        "user": "U15J5H60P",
        "ts": "1520351179.000427"
    },
    {
        "type": "message",
        "text": "I don't get it",
        "user": "U15HRTAHL",
        "ts": "1520351255.000191"
    },
    {
        "type": "message",
        "text": "Was that the story?",
        "user": "U15HRTAHL",
        "ts": "1520351258.000347"
    },
    {
        "type": "message",
        "text": "Do you have time for a call?\nYes",
        "user": "U15HRTAHL",
        "ts": "1520351286.000205"
    },
    {
        "type": "message",
        "text": "yeah?",
        "user": "U15HZ01QX",
        "ts": "1520352285.000067"
    },
    {
        "type": "message",
        "text": "I'm confused",
        "user": "U15HRTAHL",
        "ts": "1520352344.000252"
    },
    {
        "type": "message",
        "text": "me too",
        "user": "U15HZ01QX",
        "ts": "1520352349.000461"
    },
    {
        "type": "message",
        "text": "this is all I see. Am I missing something?",
        "files": [
            {
                "id": "F9L7MP12A",
                "created": 1520352366,
                "timestamp": 1520352366,
                "name": "Pasted image at 2018_03_06 10_05 AM.png",
                "title": "Pasted image at 2018-03-06, 10:05 AM",
                "mimetype": "image\/png",
                "filetype": "png",
                "pretty_type": "PNG",
                "user": "U15HRTAHL",
                "editable": false,
                "size": 85830,
                "mode": "hosted",
                "is_external": false,
                "external_type": "",
                "is_public": true,
                "public_url_shared": false,
                "display_as_bot": false,
                "username": "",
                "url_private": "https:\/\/files.slack.com\/files-pri\/T15HR7G14-F9L7MP12A\/pasted_image_at_2018_03_06_10_05_am.png?t=xoxe-39603254038-632282913120-620827978611-790c09c056a65e291519f1f9c44516dc",
                "url_private_download": "https:\/\/files.slack.com\/files-pri\/T15HR7G14-F9L7MP12A\/download\/pasted_image_at_2018_03_06_10_05_am.png?t=xoxe-39603254038-632282913120-620827978611-790c09c056a65e291519f1f9c44516dc",
                "thumb_64": "https:\/\/files.slack.com\/files-tmb\/T15HR7G14-F9L7MP12A-8b47685c87\/pasted_image_at_2018_03_06_10_05_am_64.png?t=xoxe-39603254038-632282913120-620827978611-790c09c056a65e291519f1f9c44516dc",
                "thumb_80": "https:\/\/files.slack.com\/files-tmb\/T15HR7G14-F9L7MP12A-8b47685c87\/pasted_image_at_2018_03_06_10_05_am_80.png?t=xoxe-39603254038-632282913120-620827978611-790c09c056a65e291519f1f9c44516dc",
                "thumb_360": "https:\/\/files.slack.com\/files-tmb\/T15HR7G14-F9L7MP12A-8b47685c87\/pasted_image_at_2018_03_06_10_05_am_360.png?t=xoxe-39603254038-632282913120-620827978611-790c09c056a65e291519f1f9c44516dc",
                "thumb_360_w": 360,
                "thumb_360_h": 140,
                "thumb_480": "https:\/\/files.slack.com\/files-tmb\/T15HR7G14-F9L7MP12A-8b47685c87\/pasted_image_at_2018_03_06_10_05_am_480.png?t=xoxe-39603254038-632282913120-620827978611-790c09c056a65e291519f1f9c44516dc",
                "thumb_480_w": 480,
                "thumb_480_h": 187,
                "thumb_160": "https:\/\/files.slack.com\/files-tmb\/T15HR7G14-F9L7MP12A-8b47685c87\/pasted_image_at_2018_03_06_10_05_am_160.png?t=xoxe-39603254038-632282913120-620827978611-790c09c056a65e291519f1f9c44516dc",
                "thumb_720": "https:\/\/files.slack.com\/files-tmb\/T15HR7G14-F9L7MP12A-8b47685c87\/pasted_image_at_2018_03_06_10_05_am_720.png?t=xoxe-39603254038-632282913120-620827978611-790c09c056a65e291519f1f9c44516dc",
                "thumb_720_w": 720,
                "thumb_720_h": 280,
                "thumb_800": "https:\/\/files.slack.com\/files-tmb\/T15HR7G14-F9L7MP12A-8b47685c87\/pasted_image_at_2018_03_06_10_05_am_800.png?t=xoxe-39603254038-632282913120-620827978611-790c09c056a65e291519f1f9c44516dc",
                "thumb_800_w": 800,
                "thumb_800_h": 311,
                "thumb_960": "https:\/\/files.slack.com\/files-tmb\/T15HR7G14-F9L7MP12A-8b47685c87\/pasted_image_at_2018_03_06_10_05_am_960.png?t=xoxe-39603254038-632282913120-620827978611-790c09c056a65e291519f1f9c44516dc",
                "thumb_960_w": 960,
                "thumb_960_h": 373,
                "thumb_1024": "https:\/\/files.slack.com\/files-tmb\/T15HR7G14-F9L7MP12A-8b47685c87\/pasted_image_at_2018_03_06_10_05_am_1024.png?t=xoxe-39603254038-632282913120-620827978611-790c09c056a65e291519f1f9c44516dc",
                "thumb_1024_w": 1024,
                "thumb_1024_h": 398,
                "image_exif_rotation": 1,
                "original_w": 1050,
                "original_h": 408,
                "permalink": "https:\/\/freeuwmke.slack.com\/files\/U15HRTAHL\/F9L7MP12A\/pasted_image_at_2018_03_06_10_05_am.png",
                "permalink_public": "https:\/\/slack-files.com\/T15HR7G14-F9L7MP12A-eef3646e69",
                "has_rich_preview": false
            }
        ],
        "upload": true,
        "user": "U15HRTAHL",
        "display_as_bot": false,
        "ts": "1520352370.000102"
    },
    {
        "type": "message",
        "text": "\"WHEN\"",
        "user": "U15J5H60P",
        "ts": "1520352531.000526"
    },
    {
        "type": "message",
        "text": "is the key word",
        "user": "U15J5H60P",
        "ts": "1520352533.000654"
    },
    {
        "type": "message",
        "text": "LOL",
        "user": "U15HRTAHL",
        "ts": "1520352548.000509"
    },
    {
        "type": "message",
        "text": "Anyways, I think that is saying \"I have time for a call now.\"",
        "user": "U15J5H60P",
        "ts": "1520352552.000391"
    },
    {
        "type": "message",
        "text": "it was lol",
        "user": "U15HZ01QX",
        "ts": "1520352557.000830"
    },
    {
        "type": "message",
        "text": "I read it the same way as purna",
        "user": "U15HRTAHL",
        "ts": "1520352559.000270"
    },
    {
        "type": "message",
        "text": "nvm",
        "user": "U15HRTAHL",
        "ts": "1520352579.000535"
    },
    {
        "type": "message",
        "text": "Did you ever figure out that command line thing <@U15HZ01QX>",
        "user": "U15HRTAHL",
        "ts": "1520354901.000247"
    },
    {
        "type": "message",
        "text": "Im working on it now,  I've tried every single trick I could think of",
        "user": "U15HZ01QX",
        "ts": "1520354936.000498"
    },
    {
        "type": "message",
        "text": "lol just post on stack overflow",
        "user": "U15HRTAHL",
        "ts": "1520354962.000310"
    },
    {
        "type": "message",
        "text": "What is the exact script you're trying to run",
        "user": "U15J5H60P",
        "ts": "1520355003.000855"
    },
    {
        "type": "message",
        "text": "nvm\\",
        "user": "U15J5H60P",
        "ts": "1520355031.000292"
    },
    {
        "type": "message",
        "text": "<@U15HRTAHL> coming soon",
        "user": "U15HZ01QX",
        "ts": "1520355045.000357"
    },
    {
        "type": "message",
        "text": "Your dev couldn't help you?",
        "user": "U15J5H60P",
        "ts": "1520355235.000710"
    },
    {
        "type": "message",
        "text": "No",
        "user": "U15HZ01QX",
        "ts": "1520355252.000032"
    },
    {
        "type": "message",
        "text": "Nice way to induce a heart attack at home if you’re having a bad day.\n\n<http:\/\/Amazon.com|Amazon.com> : Aduro Sport Peak Resistance High Altitude Training Mask, Camo : Sports &amp; Outdoors\n<https:\/\/www.amazon.com\/Aduro-Sport-Workout-Training-Mask\/dp\/B074RD54GH>",
        "user": "U15HZ01QX",
        "ts": "1520358685.000441"
    },
    {
        "type": "message",
        "text": "<@U15HZ01QX> the devs couldn't figure it out? or they couldn't help you?",
        "user": "U15HSHSS2",
        "ts": "1520359597.000173"
    },
    {
        "client_msg_id": "BF2BE67E-1141-422F-99B2-B2D13E86AB1F",
        "type": "message",
        "text": "I explained the problem and I think they got it. They just haven’t come up with a solution yet ",
        "user": "U15HZ01QX",
        "ts": "1520359654.000223"
    },
    {
        "client_msg_id": "1B6EA62E-E71E-4FF8-B432-74655CEA8170",
        "type": "message",
        "text": "They think having it read from another file will solve it",
        "user": "U15HZ01QX",
        "ts": "1520359687.000348"
    },
    {
        "client_msg_id": "9761E30C-6C60-4762-BE07-62C481118E79",
        "type": "message",
        "text": "WHO ARE THESE FINANCIAL ADVISORS and why do they want to add me on linkedIn",
        "user": "U15HY5TG8",
        "ts": "1520367927.000490"
    },
    {
        "client_msg_id": "6DCCFAF6-9F01-4EB5-B352-55BF12A651BC",
        "type": "message",
        "text": "You literally answered your own question ",
        "user": "U15HZ01QX",
        "ts": "1520367950.000671"
    },
    {
        "client_msg_id": "D8460302-6670-4F50-9534-75DFCB9B1FE2",
        "type": "message",
        "text": "How do you figure",
        "user": "U15HY5TG8",
        "ts": "1520367972.000199"
    },
    {
        "client_msg_id": "0051843A-18A0-4024-AADE-585BD624A46B",
        "type": "message",
        "text": "Actually...fair point. New question",
        "user": "U15HY5TG8",
        "ts": "1520368027.000023"
    },
    {
        "client_msg_id": "9CCC24F2-1686-4BB5-BF03-F56F0D0C2EF5",
        "type": "message",
        "text": "WHY CANT THEY LEAVE ME ALONE",
        "user": "U15HY5TG8",
        "ts": "1520368034.000155"
    },
    {
        "client_msg_id": "82833846-D29C-4523-A14A-8D96514040A8",
        "type": "message",
        "text": "They add you and offer you their services in case you don’t have one",
        "user": "U15HZ01QX",
        "ts": "1520368074.000379"
    },
    {
        "client_msg_id": "42E0977F-B26E-483B-9EC3-797555DE10FF",
        "type": "message",
        "text": "do people actually use financial advisors if theyre poor?",
        "user": "U15HY5TG8",
        "ts": "1520368102.000655"
    },
    {
        "client_msg_id": "8FB05D34-7DD5-417A-8844-2CB552A78548",
        "type": "message",
        "text": "Yeah",
        "user": "U15HZ01QX",
        "ts": "1520368110.000518"
    },
    {
        "type": "message",
        "text": "Read that as \"They add you to offer their services to make money\"",
        "user": "U15HRTAHL",
        "ts": "1520368119.000173"
    },
    {
        "type": "message",
        "text": "no one is that nice",
        "user": "U15HRTAHL",
        "ts": "1520368122.000191"
    },
    {
        "type": "message",
        "text": "pro bono",
        "user": "U15HRTAHL",
        "ts": "1520368125.000231",
        "edited": {
            "user": "U15HRTAHL",
            "ts": "1520368127.000000"
        }
    },
    {
        "client_msg_id": "C1463A19-7A03-4018-B984-EB933287CBEB",
        "type": "message",
        "text": "It’s debatable whether it’s smart for poor people to use them",
        "user": "U15HZ01QX",
        "ts": "1520368154.000545"
    },
    {
        "client_msg_id": "41C85660-EEE8-48AC-9222-D394C83FC76E",
        "type": "message",
        "text": "They make money, you make money. Win win ",
        "user": "U15J5H60P",
        "ts": "1520368161.000619"
    },
    {
        "client_msg_id": "25D3B3F6-74AF-4ECA-9F52-30D1F6B115A1",
        "type": "message",
        "text": "But I’m sure they do",
        "user": "U15HZ01QX",
        "ts": "1520368161.000720"
    },
    {
        "client_msg_id": "2293FE62-A2E0-40D0-8C21-A872AAAF5510",
        "type": "message",
        "text": "They don't always sell you services",
        "user": "U15J5H60P",
        "ts": "1520368171.000368"
    },
    {
        "client_msg_id": "8FF4AEDD-9084-4699-8C79-2B8E46CE1CE9",
        "type": "message",
        "text": "Sometimes they have to help you get to a position in which you can buy their services",
        "user": "U15J5H60P",
        "ts": "1520368186.000225"
    },
    {
        "client_msg_id": "B67A0FD5-6D28-445C-90EE-4A877889C3C2",
        "type": "message",
        "text": "They really are a lot better than you'd think. ",
        "user": "U15J5H60P",
        "ts": "1520368207.000305"
    },
    {
        "client_msg_id": "E92A24D8-BB2F-4784-A8DC-AE04904D79F1",
        "type": "message",
        "text": "Didn’t know that.",
        "user": "U15HZ01QX",
        "ts": "1520368214.000692"
    },
    {
        "client_msg_id": "B1E057B2-A864-449D-A4EE-BEC113C04BDB",
        "type": "message",
        "text": "Interesting",
        "user": "U15HY5TG8",
        "ts": "1520368222.000713"
    },
    {
        "client_msg_id": "9BB106F5-1BA7-46FF-93D9-ED9D1FC7A3BA",
        "type": "message",
        "text": "Will they calculate my crypto?",
        "user": "U15HY5TG8",
        "ts": "1520368231.000650"
    },
    {
        "type": "message",
        "text": "Keep in mind andrew works at a financial services company.",
        "user": "U15HRTAHL",
        "ts": "1520368239.000193"
    },
    {
        "client_msg_id": "A8BBA481-A349-4479-9233-3BF78396F817",
        "type": "message",
        "text": "Yeah",
        "user": "U15J5H60P",
        "ts": "1520368243.000418"
    },
    {
        "type": "message",
        "text": "hes getting kick backs",
        "user": "U15HRTAHL",
        "ts": "1520368244.000154"
    },
    {
        "client_msg_id": "0299DCA1-8530-40BD-8797-BBA04346DC91",
        "type": "message",
        "text": "So I know how it works ",
        "user": "U15J5H60P",
        "ts": "1520368247.000525"
    },
    {
        "client_msg_id": "4861C990-DD26-48E1-BA6E-50B484A693FB",
        "type": "message",
        "text": "Lol",
        "user": "U15J5H60P",
        "ts": "1520368249.000309"
    },
    {
        "type": "message",
        "text": "its andrew adding you",
        "user": "U15HRTAHL",
        "ts": "1520368257.000212"
    },
    {
        "client_msg_id": "A30A61AE-725B-4ECE-A4F7-083B5C0E523C",
        "type": "message",
        "text": "Lol SHILLING",
        "user": "U15HZ01QX",
        "ts": "1520368258.000370"
    },
    {
        "type": "message",
        "text": "ghost accounts",
        "user": "U15HRTAHL",
        "ts": "1520368260.000150"
    },
    {
        "client_msg_id": "24978EC9-0B45-4162-9D68-F38B613C538C",
        "type": "message",
        "text": "Lol",
        "user": "U15HY5TG8",
        "ts": "1520368271.000292"
    },
    {
        "client_msg_id": "6A245C95-B99D-4F58-85CB-19D7554033C0",
        "type": "message",
        "text": "I'd recommend y'all get one whether it's here or not ",
        "user": "U15J5H60P",
        "ts": "1520368273.000319"
    },
    {
        "client_msg_id": "1D7EEF6C-FBEB-4FA3-9B30-2D4CA27B72B1",
        "type": "message",
        "text": "You don't need to buy anything, but they're nice to talk to",
        "user": "U15J5H60P",
        "ts": "1520368290.000507"
    },
    {
        "client_msg_id": "17904671-7158-4239-8A7A-F3297EE8DCBA",
        "type": "message",
        "text": "Prob not. Im too much of a hippie",
        "user": "U15HY5TG8",
        "ts": "1520368291.000322"
    },
    {
        "client_msg_id": "C860282D-7A3C-437D-B5E5-25653E515C23",
        "type": "message",
        "text": "Fair enough. ",
        "user": "U15J5H60P",
        "ts": "1520368296.000414"
    },
    {
        "type": "message",
        "text": "All you need to do is throw money into a 401k and live within your means. if you start a family get some life insurance. Easy peasy",
        "user": "U15HRTAHL",
        "ts": "1520368340.000151"
    },
    {
        "type": "message",
        "text": "Now that advice will cost you $100",
        "user": "U15HRTAHL",
        "ts": "1520368347.000126"
    },
    {
        "client_msg_id": "14E5458E-96EB-4CE6-99C3-DE2B7598EF04",
        "type": "message",
        "text": "Educators will advise you for free",
        "user": "U15HZ01QX",
        "ts": "1520368348.000238"
    },
    {
        "client_msg_id": "EFB21A68-B9CB-457C-92CE-9E81EE4DBF20",
        "type": "message",
        "text": "Yerrrr <https:\/\/freeuwmke.slack.com\/archives\/C15HP1TGC\/p1520368340000151>",
        "user": "U15HZ01QX",
        "ts": "1520368364.000073",
        "attachments": [
            {
                "from_url": "https:\/\/freeuwmke.slack.com\/archives\/C15HP1TGC\/p1520368340000151",
                "fallback": "[March 6th, 2018 12:32 PM] joeythomaschaske: All you need to do is throw money into a 401k and live within your means. if you start a family get some life insurance. Easy peasy",
                "ts": "1520368340.000151",
                "author_id": "U15HRTAHL",
                "author_subname": "Joseph Thomaschaske",
                "channel_id": "C15HP1TGC",
                "channel_name": "general",
                "is_msg_unfurl": true,
                "text": "All you need to do is throw money into a 401k and live within your means. if you start a family get some life insurance. Easy peasy",
                "author_name": "Joseph Thomaschaske",
                "author_link": "https:\/\/freeuwmke.slack.com\/team\/U15HRTAHL",
                "author_icon": "https:\/\/avatars.slack-edge.com\/2016-05-02\/39618197601_70be165dc04ef2c7bbc5_48.jpg",
                "mrkdwn_in": [
                    "text"
                ],
                "id": 1,
                "footer": "Posted in #general"
            }
        ]
    },
    {
        "client_msg_id": "ADB0C63B-73FC-41A6-8A01-C11BF6531E57",
        "type": "message",
        "text": "Yeah, until you get cancer and can't work ",
        "user": "U15J5H60P",
        "ts": "1520368388.000147"
    },
    {
        "type": "message",
        "text": "We can schedule meetings once a month for me to repeat the same thing and review how much you've invested for $50\/session",
        "user": "U15HRTAHL",
        "ts": "1520368393.000681"
    },
    {
        "client_msg_id": "111C0F9E-4EE5-42C7-8E6D-AF6DB124B12C",
        "type": "message",
        "text": "Lol you don't pay for sessions ",
        "user": "U15J5H60P",
        "ts": "1520368414.000243"
    },
    {
        "client_msg_id": "42E23BF1-5701-401B-BCEB-C86D3662CA31",
        "type": "message",
        "text": "Lol",
        "user": "U15HY5TG8",
        "ts": "1520368424.000051"
    },
    {
        "client_msg_id": "44A35BC4-1711-45FB-B9B4-1878AB3EF7DC",
        "type": "message",
        "text": "What advice can be given to someone who can’t work",
        "user": "U15HZ01QX",
        "ts": "1520368424.000239"
    },
    {
        "client_msg_id": "EBA750B4-32F6-4828-A1AB-34A3B06A7870",
        "type": "message",
        "text": "401k is dead",
        "user": "U15HY5TG8",
        "ts": "1520368430.000607"
    },
    {
        "type": "message",
        "text": "I'm a fiduciary, so I charge. Its for your best interest",
        "user": "U15HRTAHL",
        "ts": "1520368439.000146"
    },
    {
        "client_msg_id": "294085FD-A27E-43DB-A1E8-40DB291CD86B",
        "type": "message",
        "text": "Headass <https:\/\/freeuwmke.slack.com\/archives\/C15HP1TGC\/p1520368430000607>",
        "user": "U15HZ01QX",
        "ts": "1520368439.000387",
        "edited": {
            "user": "U15HZ01QX",
            "ts": "1520368448.000000"
        }
    },
    {
        "client_msg_id": "DF04E63C-F3E6-4A6F-92B5-FD7A80CF4E9F",
        "type": "message",
        "text": "The idea is you should've been talking to an advisor before you got cancer and should've got DI",
        "user": "U15J5H60P",
        "ts": "1520368454.000361"
    },
    {
        "type": "message",
        "text": "but sure go to a free guy so he can take your money like madoff",
        "user": "U15HRTAHL",
        "ts": "1520368456.000206"
    },
    {
        "client_msg_id": "36160020-4AA8-4D99-A070-4655CFC62FAD",
        "type": "message",
        "text": "DI?",
        "user": "U15HZ01QX",
        "ts": "1520368473.000778"
    },
    {
        "type": "message",
        "text": "Disability",
        "user": "U15HRTAHL",
        "ts": "1520368477.000330"
    },
    {
        "type": "message",
        "text": "Insurance",
        "user": "U15HRTAHL",
        "ts": "1520368479.000677"
    },
    {
        "client_msg_id": "E856DBC5-BF85-49AF-80A3-50DB5F234A19",
        "type": "message",
        "text": "Isn’t that a government benefit? What I need an advisor for",
        "user": "U15HZ01QX",
        "ts": "1520368506.000457"
    },
    {
        "type": "message",
        "text": "No you pay out of pocket for that lol",
        "user": "U15HRTAHL",
        "ts": "1520368520.000559"
    },
    {
        "client_msg_id": "E11989A3-4FB6-49E9-93AA-F6CA4A98FDCA",
        "type": "message",
        "text": "With your health insurance stuff right?",
        "user": "U15HZ01QX",
        "ts": "1520368539.000228"
    },
    {
        "client_msg_id": "7E7FAF1F-F709-4B7B-8F56-559EE83ADE76",
        "type": "message",
        "text": "Maybe you'll get some social security benefits ",
        "user": "U15J5H60P",
        "ts": "1520368540.000577"
    },
    {
        "type": "message",
        "text": "damn govt expects you to work so they get paid",
        "user": "U15HRTAHL",
        "ts": "1520368540.000590"
    },
    {
        "client_msg_id": "2A63A785-B696-41AD-8A26-9A37E6EC25AD",
        "type": "message",
        "text": "But DI covers more",
        "user": "U15J5H60P",
        "ts": "1520368555.000535"
    },
    {
        "client_msg_id": "23B03B10-7A6B-450B-A7ED-4345B7EB3362",
        "type": "message",
        "text": "Plus it's super cheap from what I hear",
        "user": "U15J5H60P",
        "ts": "1520368567.000440"
    },
    {
        "client_msg_id": "594DFA72-1FBA-4E85-B086-3AA38A77ABF1",
        "type": "message",
        "text": "But it’s not through your company?",
        "user": "U15HZ01QX",
        "ts": "1520368575.000112"
    },
    {
        "type": "message",
        "text": "its like $20 a month",
        "user": "U15HRTAHL",
        "ts": "1520368585.000096"
    },
    {
        "client_msg_id": "EA90D968-93CB-4468-B857-6F9F7C81A34E",
        "type": "message",
        "text": "Your company usually covers a percentage",
        "user": "U15J5H60P",
        "ts": "1520368589.000379"
    },
    {
        "type": "message",
        "text": "Scott has it",
        "user": "U15HRTAHL",
        "ts": "1520368591.000356"
    },
    {
        "client_msg_id": "2C62C508-B79A-48B9-95A0-50D0758036A4",
        "type": "message",
        "text": "DI covers the rest",
        "user": "U15J5H60P",
        "ts": "1520368596.000431"
    },
    {
        "client_msg_id": "C5F39F39-FA1F-4BF0-B79B-A7E976BC0734",
        "type": "message",
        "text": "Also",
        "user": "U15J5H60P",
        "ts": "1520368621.000467"
    },
    {
        "client_msg_id": "22D87E9C-9550-41AD-BDE4-2EAED6F0FC7B",
        "type": "message",
        "text": "Company DI only lasts so long",
        "user": "U15J5H60P",
        "ts": "1520368629.000313"
    },
    {
        "type": "message",
        "text": "",
        "files": [
            {
                "id": "F9K1KQN1F",
                "created": 1520368655,
                "timestamp": 1520368655,
                "name": "Pasted image at 2018_03_06 02_37 PM.png",
                "title": "Pasted image at 2018-03-06, 2:37 PM",
                "mimetype": "image\/png",
                "filetype": "png",
                "pretty_type": "PNG",
                "user": "U15HRTAHL",
                "editable": false,
                "size": 305476,
                "mode": "hosted",
                "is_external": false,
                "external_type": "",
                "is_public": true,
                "public_url_shared": false,
                "display_as_bot": false,
                "username": "",
                "url_private": "https:\/\/files.slack.com\/files-pri\/T15HR7G14-F9K1KQN1F\/pasted_image_at_2018_03_06_02_37_pm.png?t=xoxe-39603254038-632282913120-620827978611-790c09c056a65e291519f1f9c44516dc",
                "url_private_download": "https:\/\/files.slack.com\/files-pri\/T15HR7G14-F9K1KQN1F\/download\/pasted_image_at_2018_03_06_02_37_pm.png?t=xoxe-39603254038-632282913120-620827978611-790c09c056a65e291519f1f9c44516dc",
                "thumb_64": "https:\/\/files.slack.com\/files-tmb\/T15HR7G14-F9K1KQN1F-ac63df939b\/pasted_image_at_2018_03_06_02_37_pm_64.png?t=xoxe-39603254038-632282913120-620827978611-790c09c056a65e291519f1f9c44516dc",
                "thumb_80": "https:\/\/files.slack.com\/files-tmb\/T15HR7G14-F9K1KQN1F-ac63df939b\/pasted_image_at_2018_03_06_02_37_pm_80.png?t=xoxe-39603254038-632282913120-620827978611-790c09c056a65e291519f1f9c44516dc",
                "thumb_360": "https:\/\/files.slack.com\/files-tmb\/T15HR7G14-F9K1KQN1F-ac63df939b\/pasted_image_at_2018_03_06_02_37_pm_360.png?t=xoxe-39603254038-632282913120-620827978611-790c09c056a65e291519f1f9c44516dc",
                "thumb_360_w": 360,
                "thumb_360_h": 278,
                "thumb_480": "https:\/\/files.slack.com\/files-tmb\/T15HR7G14-F9K1KQN1F-ac63df939b\/pasted_image_at_2018_03_06_02_37_pm_480.png?t=xoxe-39603254038-632282913120-620827978611-790c09c056a65e291519f1f9c44516dc",
                "thumb_480_w": 480,
                "thumb_480_h": 371,
                "thumb_160": "https:\/\/files.slack.com\/files-tmb\/T15HR7G14-F9K1KQN1F-ac63df939b\/pasted_image_at_2018_03_06_02_37_pm_160.png?t=xoxe-39603254038-632282913120-620827978611-790c09c056a65e291519f1f9c44516dc",
                "thumb_720": "https:\/\/files.slack.com\/files-tmb\/T15HR7G14-F9K1KQN1F-ac63df939b\/pasted_image_at_2018_03_06_02_37_pm_720.png?t=xoxe-39603254038-632282913120-620827978611-790c09c056a65e291519f1f9c44516dc",
                "thumb_720_w": 720,
                "thumb_720_h": 556,
                "thumb_800": "https:\/\/files.slack.com\/files-tmb\/T15HR7G14-F9K1KQN1F-ac63df939b\/pasted_image_at_2018_03_06_02_37_pm_800.png?t=xoxe-39603254038-632282913120-620827978611-790c09c056a65e291519f1f9c44516dc",
                "thumb_800_w": 800,
                "thumb_800_h": 618,
                "thumb_960": "https:\/\/files.slack.com\/files-tmb\/T15HR7G14-F9K1KQN1F-ac63df939b\/pasted_image_at_2018_03_06_02_37_pm_960.png?t=xoxe-39603254038-632282913120-620827978611-790c09c056a65e291519f1f9c44516dc",
                "thumb_960_w": 960,
                "thumb_960_h": 741,
                "thumb_1024": "https:\/\/files.slack.com\/files-tmb\/T15HR7G14-F9K1KQN1F-ac63df939b\/pasted_image_at_2018_03_06_02_37_pm_1024.png?t=xoxe-39603254038-632282913120-620827978611-790c09c056a65e291519f1f9c44516dc",
                "thumb_1024_w": 1024,
                "thumb_1024_h": 790,
                "image_exif_rotation": 1,
                "original_w": 1394,
                "original_h": 1076,
                "permalink": "https:\/\/freeuwmke.slack.com\/files\/U15HRTAHL\/F9K1KQN1F\/pasted_image_at_2018_03_06_02_37_pm.png",
                "permalink_public": "https:\/\/slack-files.com\/T15HR7G14-F9K1KQN1F-d2208e2aad",
                "has_rich_preview": false
            }
        ],
        "upload": true,
        "user": "U15HRTAHL",
        "display_as_bot": false,
        "ts": "1520368658.000313"
    },
    {
        "type": "message",
        "text": "<https:\/\/www.thebalance.com\/what-is-long-term-disability-insurance-1918178>",
        "user": "U15J5H60P",
        "ts": "1520368679.000580",
        "attachments": [
            {
                "service_name": "The Balance",
                "title": "What Is Long-Term and Short-Term Disability Insurance?",
                "title_link": "https:\/\/www.thebalance.com\/what-is-long-term-disability-insurance-1918178",
                "text": "Find out more about how long-term and short-term disability insurance are preferred benefits for employees that ensure income during an extended illness.",
                "fallback": "The Balance: What Is Long-Term and Short-Term Disability Insurance?",
                "thumb_url": "https:\/\/fthmb.tqn.com\/SBk6p-KWybyRsXZYkepfqdRIzq4=\/5116x3415\/filters:fill(auto,1)\/nurse-using-digital-tablet-with-patient-in-hospital-503848511-57d5d27c3df78c58335cba29.jpg",
                "from_url": "https:\/\/www.thebalance.com\/what-is-long-term-disability-insurance-1918178",
                "thumb_width": 5116,
                "thumb_height": 3415,
                "service_icon": "https:\/\/www.thebalance.com\/static\/2.86.0\/icons\/favicons\/apple-touch-icon-57x57.png",
                "id": 1
            }
        ]
    },
    {
        "client_msg_id": "4672BCB5-4833-47EB-A1E2-77AB9FC957FE",
        "type": "message",
        "text": "Guess I better go pick some of that up",
        "user": "U15HZ01QX",
        "ts": "1520368698.000460"
    },
    {
        "type": "message",
        "text": "lol",
        "user": "U15J5H60P",
        "ts": "1520368714.000694"
    },
    {
        "client_msg_id": "DDBB1D47-7A94-4A65-8A63-F64B54B7BF39",
        "type": "message",
        "text": "20 bucks a month is kinda steep lol",
        "user": "U15HZ01QX",
        "ts": "1520368752.000237"
    },
    {
        "client_msg_id": "951592C5-6CD3-4B85-AA4A-7B5969E65F5E",
        "type": "message",
        "text": "Unless it includes layoff insurance ",
        "user": "U15HZ01QX",
        "ts": "1520368766.000200"
    },
    {
        "type": "message",
        "text": "lol Nope",
        "user": "U15J5H60P",
        "ts": "1520368770.000731"
    }
]