[
    {
        "type": "message",
        "text": "It's a rare day where I've got nothing to do",
        "user": "U15HRTAHL",
        "ts": "1517413457.000343"
    },
    {
        "type": "message",
        "text": "So one of my managers from work pulled me aside to see if i wanted to do a project outside of work for a friend of his wife",
        "user": "U15HY5TG8",
        "ts": "1517450501.000043"
    },
    {
        "type": "message",
        "text": "Nice!",
        "user": "U15J5H60P",
        "ts": "1517450793.000237"
    },
    {
        "type": "message",
        "text": "You're going to be a porn star!",
        "user": "U15J5H60P",
        "ts": "1517450803.000165",
        "reactions": [
            {
                "name": "+1::skin-tone-5",
                "users": [
                    "U15HSHSS2",
                    "U15HRTAHL"
                ],
                "count": 2
            }
        ]
    },
    {
        "type": "message",
        "text": "Lol wat",
        "user": "U15HY5TG8",
        "ts": "1517450886.000290"
    },
    {
        "type": "message",
        "text": "LOL",
        "user": "U15HRTAHL",
        "ts": "1517454362.000149"
    }
]